a_mail/__init__.py
a_mail/core/__init__.py
a_mail/core/agent.py
a_mail/core/agent_tool.py
a_mail/core/graph.py
a_mail/core/printer.py
a_mail/core/state.py
a_mail/core/sys_prompt.py
a_mail/utils/__init__.py
a_mail/utils/loader.py
a_mail/utils/parse_output.py
a_mailx-0.1.0.dist-info/licenses/LICENSE
a_mailx-0.1.0.dist-info/METADATA
a_mailx-0.1.0.dist-info/WHEEL
a_mailx-0.1.0.dist-info/top_level.txt
a_mailx-0.1.0.dist-info/RECORD
