Metadata-Version: 2.4
Name: a_mailx
Version: 0.1.0
Summary: A Multi-Agent Communication Protocol Solution Based on LangGraph
Home-page: https://github.com/dev-yang-ai/A_mail
Author: yanghhhhh
Author-email: developer_yang@qq.com
Classifier: Programming Language :: Python :: 3
Classifier: License :: OSI Approved :: MIT License
Classifier: Operating System :: OS Independent
Requires-Python: >=3.11
License-File: LICENSE
Requires-Dist: addict==2.4.0
Requires-Dist: aiohappyeyeballs==2.6.1
Requires-Dist: aiohttp==3.12.15
Requires-Dist: aiosignal==1.4.0
Requires-Dist: aiosqlite==0.21.0
Requires-Dist: annotated-types==0.7.0
Requires-Dist: anthropic==0.64.0
Requires-Dist: anyio==4.10.0
Requires-Dist: argon2-cffi==25.1.0
Requires-Dist: argon2-cffi-bindings==25.1.0
Requires-Dist: arrow==1.3.0
Requires-Dist: asttokens==3.0.0
Requires-Dist: async-lru==2.0.5
Requires-Dist: attrs==25.3.0
Requires-Dist: babel==2.17.0
Requires-Dist: beautifulsoup4==4.13.4
Requires-Dist: bleach==6.2.0
Requires-Dist: certifi==2025.8.3
Requires-Dist: cffi==1.17.1
Requires-Dist: charset-normalizer==3.4.2
Requires-Dist: click==8.2.1
Requires-Dist: colorama==0.4.6
Requires-Dist: comm==0.2.3
Requires-Dist: dataclasses-json==0.6.7
Requires-Dist: datasets==1.18.4
Requires-Dist: ddgs==9.5.2
Requires-Dist: debugpy==1.8.16
Requires-Dist: decorator==5.2.1
Requires-Dist: defusedxml==0.7.1
Requires-Dist: dill==0.3.8
Requires-Dist: distro==1.9.0
Requires-Dist: duckduckgo_search==8.1.1
Requires-Dist: executing==2.2.0
Requires-Dist: fastjsonschema==2.21.1
Requires-Dist: filelock==3.18.0
Requires-Dist: fqdn==1.5.1
Requires-Dist: frozenlist==1.7.0
Requires-Dist: fsspec==2024.2.0
Requires-Dist: greenlet==3.2.3
Requires-Dist: h11==0.16.0
Requires-Dist: httpcore==1.0.9
Requires-Dist: httpx==0.28.1
Requires-Dist: httpx-sse==0.4.1
Requires-Dist: huggingface-hub==0.34.3
Requires-Dist: idna==3.10
Requires-Dist: ipykernel==6.30.1
Requires-Dist: ipython==9.4.0
Requires-Dist: ipython_pygments_lexers==1.1.1
Requires-Dist: isoduration==20.11.0
Requires-Dist: jedi==0.19.2
Requires-Dist: Jinja2==3.1.6
Requires-Dist: jiter==0.10.0
Requires-Dist: json5==0.12.0
Requires-Dist: json_repair==0.40.0
Requires-Dist: jsonpatch==1.33
Requires-Dist: jsonpointer==3.0.0
Requires-Dist: jsonschema==4.25.0
Requires-Dist: jsonschema-specifications==2025.4.1
Requires-Dist: jupyter-events==0.12.0
Requires-Dist: jupyter-lsp==2.2.6
Requires-Dist: jupyter_client==8.6.3
Requires-Dist: jupyter_core==5.8.1
Requires-Dist: jupyter_server==2.16.0
Requires-Dist: jupyter_server_terminals==0.5.3
Requires-Dist: jupyterlab==4.4.5
Requires-Dist: jupyterlab_pygments==0.3.0
Requires-Dist: jupyterlab_server==2.27.3
Requires-Dist: langchain==0.3.27
Requires-Dist: langchain-anthropic==0.3.18
Requires-Dist: langchain-community==0.3.27
Requires-Dist: langchain-core==0.3.74
Requires-Dist: langchain-deepseek==0.1.4
Requires-Dist: langchain-openai==0.3.28
Requires-Dist: langchain-qwq==0.2.0
Requires-Dist: langchain-text-splitters==0.3.9
Requires-Dist: langgraph==0.6.4
Requires-Dist: langgraph-checkpoint==2.1.1
Requires-Dist: langgraph-checkpoint-sqlite==2.0.11
Requires-Dist: langgraph-prebuilt==0.6.4
Requires-Dist: langgraph-sdk==0.2.0
Requires-Dist: langsmith==0.4.11
Requires-Dist: lark==1.2.2
Requires-Dist: lxml==6.0.0
Requires-Dist: MarkupSafe==3.0.2
Requires-Dist: marshmallow==3.26.1
Requires-Dist: matplotlib-inline==0.1.7
Requires-Dist: mistune==3.1.3
Requires-Dist: modelscope==1.28.2
Requires-Dist: multidict==6.6.3
Requires-Dist: multiprocess==0.70.16
Requires-Dist: mypy_extensions==1.1.0
Requires-Dist: nbclient==0.10.2
Requires-Dist: nbconvert==7.16.6
Requires-Dist: nbformat==5.10.4
Requires-Dist: nest-asyncio==1.6.0
Requires-Dist: notebook==7.4.5
Requires-Dist: notebook_shim==0.2.4
Requires-Dist: numpy==2.3.2
Requires-Dist: openai==1.98.0
Requires-Dist: orjson==3.11.1
Requires-Dist: ormsgpack==1.10.0
Requires-Dist: overrides==7.7.0
Requires-Dist: packaging==25.0
Requires-Dist: pandas==2.3.1
Requires-Dist: pandocfilters==1.5.1
Requires-Dist: parso==0.8.4
Requires-Dist: platformdirs==4.3.8
Requires-Dist: primp==0.15.0
Requires-Dist: prometheus_client==0.22.1
Requires-Dist: prompt_toolkit==3.0.51
Requires-Dist: propcache==0.3.2
Requires-Dist: psutil==7.0.0
Requires-Dist: pure_eval==0.2.3
Requires-Dist: pyarrow-hotfix==0.7
Requires-Dist: pycparser==2.22
Requires-Dist: pydantic==2.11.7
Requires-Dist: pydantic-settings==2.10.1
Requires-Dist: pydantic_core==2.33.2
Requires-Dist: Pygments==2.19.2
Requires-Dist: python-dateutil==2.9.0.post0
Requires-Dist: python-dotenv==1.1.1
Requires-Dist: python-json-logger==3.3.0
Requires-Dist: pytz==2025.2
Requires-Dist: pywin32==311
Requires-Dist: pywinpty==2.0.15
Requires-Dist: PyYAML==6.0.2
Requires-Dist: pyzmq==27.0.1
Requires-Dist: referencing==0.36.2
Requires-Dist: regex==2025.7.34
Requires-Dist: requests==2.32.4
Requires-Dist: requests-toolbelt==1.0.0
Requires-Dist: responses==0.18.0
Requires-Dist: rfc3339-validator==0.1.4
Requires-Dist: rfc3986-validator==0.1.1
Requires-Dist: rfc3987-syntax==1.1.0
Requires-Dist: rpds-py==0.27.0
Requires-Dist: Send2Trash==1.8.3
Requires-Dist: setuptools==78.1.1
Requires-Dist: six==1.17.0
Requires-Dist: sniffio==1.3.1
Requires-Dist: soupsieve==2.7
Requires-Dist: SQLAlchemy==2.0.42
Requires-Dist: sqlite-vec==0.1.6
Requires-Dist: stack-data==0.6.3
Requires-Dist: tenacity==9.1.2
Requires-Dist: terminado==0.18.1
Requires-Dist: tiktoken==0.9.0
Requires-Dist: tinycss2==1.4.0
Requires-Dist: toml==0.10.2
Requires-Dist: tomli==2.2.1
Requires-Dist: tornado==6.5.2
Requires-Dist: tqdm==4.67.1
Requires-Dist: traitlets==5.14.3
Requires-Dist: types-python-dateutil==2.9.0.20250809
Requires-Dist: typing-inspect==0.9.0
Requires-Dist: typing-inspection==0.4.1
Requires-Dist: typing_extensions==4.14.1
Requires-Dist: tzdata==2025.2
Requires-Dist: uri-template==1.3.0
Requires-Dist: urllib3==2.5.0
Requires-Dist: wcwidth==0.2.13
Requires-Dist: webcolors==24.11.1
Requires-Dist: webencodings==0.5.1
Requires-Dist: websocket-client==1.8.0
Requires-Dist: wheel==0.45.1
Requires-Dist: xxhash==3.5.0
Requires-Dist: yarl==1.20.1
Requires-Dist: zstandard==0.23.0
Dynamic: author
Dynamic: author-email
Dynamic: classifier
Dynamic: description
Dynamic: description-content-type
Dynamic: home-page
Dynamic: license-file
Dynamic: requires-dist
Dynamic: requires-python
Dynamic: summary
